bitmapindex/__init__.py
bitmapindex/bitmapindex.py
bitmapindex-0.0.1.dist-info/DESCRIPTION.rst
bitmapindex-0.0.1.dist-info/METADATA
bitmapindex-0.0.1.dist-info/RECORD
bitmapindex-0.0.1.dist-info/WHEEL
bitmapindex-0.0.1.dist-info/metadata.json
bitmapindex-0.0.1.dist-info/top_level.txt
