Metadata-Version: 2.0
Name: bitmapindex
Version: 0.0.1
Summary: A pure python bitmap index
Home-page: https://github.com/amg84/python-bitmap-index
Author: Andrew Grundy
Author-email: grundyonline@gmail.com
License: GNU GPL 3
Download-URL: https://github.com/amg84/python-bitmap-index/tarball/0.0.1
Keywords: bitmap,index
Platform: UNKNOWN
Classifier: Development Status :: 3 - Alpha
Classifier: Intended Audience :: Developers
Classifier: Programming Language :: Python :: 3.4
